MANIFEST.in
README.md
requirements.txt
setup.py
soulapi/Api.py
soulapi/Client.py
soulapi/Post.py
soulapi/Robot.py
soulapi/__init__.py
soulapi/cli.py
soulapi.egg-info/PKG-INFO
soulapi.egg-info/SOURCES.txt
soulapi.egg-info/dependency_links.txt
soulapi.egg-info/entry_points.txt
soulapi.egg-info/requires.txt
soulapi.egg-info/top_level.txt