Metadata-Version: 1.0
Name: soulapi
Version: 0.0.3
Summary: soul shell client
Home-page: https://github.com/acrazing/soulapi-api
Author: acrazing
Author-email: joking.young@gmail.com
License: MIT
Keywords: soul client api
Platform: UNKNOWN
